mappingtools/__init__.py
mappingtools/_compat.py
mappingtools/_tools.py
mappingtools/operators.py
mappingtools/typing.py
mappingtools/collectors/__init__.py
mappingtools/collectors/_collectors.py
mappingtools/collectors/mapping_collector.py
mappingtools/collectors/metered_dict.py
mappingtools/structures/__init__.py
mappingtools/structures/dictifier.py
mappingtools/structures/lazy_dictifier.py
mappingtools/transformers/__init__.py
mappingtools/transformers/listify.py
mappingtools/transformers/minify.py
mappingtools/transformers/simplify.py
mappingtools/transformers/strictify.py
mappingtools/transformers/stringify.py
mappingtools/transformers/transformer.py
mappingtools-0.9.0.dist-info/METADATA
mappingtools-0.9.0.dist-info/WHEEL
mappingtools-0.9.0.dist-info/licenses/LICENSE
mappingtools-0.9.0.dist-info/RECORD
