Metadata-Version: 2.4
Name: mappingtools
Version: 0.9.0
Summary: MappingTools. Do stuff with Mappings and more
Project-URL: Homepage, https://erivlis.github.io/mappingtools
Project-URL: Documentation, https://erivlis.github.io/mappingtools/README.md
Project-URL: Bug Tracker, https://github.com/erivlis/mappingtools/issues
Project-URL: Source, https://github.com/erivlis/mappingtools
Author-email: Eran Rivlis <eran@rivlis.info>
License-File: LICENSE
Keywords: Mapping,manipulate,mutate,transform
Classifier: Development Status :: 4 - Beta
Classifier: Intended Audience :: Developers
Classifier: Intended Audience :: Information Technology
Classifier: License :: OSI Approved :: MIT License
Classifier: Natural Language :: English
Classifier: Operating System :: OS Independent
Classifier: Programming Language :: Python :: 3
Classifier: Programming Language :: Python :: 3 :: Only
Classifier: Programming Language :: Python :: 3.10
Classifier: Programming Language :: Python :: 3.11
Classifier: Programming Language :: Python :: 3.12
Classifier: Programming Language :: Python :: 3.13
Classifier: Programming Language :: Python :: 3.14
Classifier: Programming Language :: Python :: Implementation :: CPython
Classifier: Topic :: Software Development :: Libraries
Classifier: Typing :: Typed
Requires-Python: >=3.10
Requires-Dist: deprecated>=1.3.1; python_version < '3.13'
